exifdate2fs/__init__.py
exifdate2fs-0.8.14.dist-info/LICENSE
exifdate2fs-0.8.14.dist-info/METADATA
exifdate2fs-0.8.14.dist-info/WHEEL
exifdate2fs-0.8.14.dist-info/entry_points.txt
exifdate2fs-0.8.14.dist-info/top_level.txt
exifdate2fs-0.8.14.dist-info/RECORD
