Metadata-Version: 2.1
Name: exifdate2fs
Version: 0.8.14
Summary: This tool will recursively update file timestamps to information from EXIF tag DateTimeOriginal
Home-page: https://github.com/varnav/ExifDate2FS
Author: Evgeny Varnavskiy
Author-email: varnavruz@gmail.com
Keywords: jpeg,exif,filesystem,filetime
Classifier: Development Status :: 4 - Beta
Classifier: Environment :: MacOS X
Classifier: Environment :: Win32 (MS Windows)
Classifier: Intended Audience :: End Users/Desktop
Classifier: License :: OSI Approved :: MIT License
Classifier: Operating System :: OS Independent
Classifier: Topic :: Scientific/Engineering :: Image Processing
Classifier: Topic :: Utilities
Classifier: Topic :: Multimedia :: Graphics
Classifier: Environment :: Console
Classifier: Programming Language :: Python :: 3.9
Classifier: Programming Language :: Python :: 3 :: Only
Requires-Python: >=3.7
License-File: LICENSE
Requires-Dist: exifread (<3)
Requires-Dist: win32-setctime ; platform_system == "Windows"
